README.md
pyproject.toml
ommx_highs_adapter/__init__.py
ommx_highs_adapter/adapter.py
ommx_highs_adapter/exception.py
ommx_highs_adapter.egg-info/PKG-INFO
ommx_highs_adapter.egg-info/SOURCES.txt
ommx_highs_adapter.egg-info/dependency_links.txt
ommx_highs_adapter.egg-info/requires.txt
ommx_highs_adapter.egg-info/top_level.txt
tests/test_adapter.py
tests/test_error.py